analitiqs/__init__.py
analitiqs/etl.py
analitiqs-0.0.7.dist-info/METADATA
analitiqs-0.0.7.dist-info/WHEEL
analitiqs-0.0.7.dist-info/top_level.txt
analitiqs-0.0.7.dist-info/RECORD
